antwerpen/__init__.py
antwerpen/antwerpen.py
antwerpen/exceptions.py
antwerpen/models.py
antwerpen/py.typed
antwerpen-1.1.0.dist-info/METADATA
antwerpen-1.1.0.dist-info/WHEEL
antwerpen-1.1.0.dist-info/licenses/LICENSE
antwerpen-1.1.0.dist-info/RECORD
